oarepo_global_search/__init__.py
oarepo_global_search/config.py
oarepo_global_search/ext.py
oarepo_global_search/info.py
oarepo_global_search/proxies.py
oarepo_global_search/i18n/__init__.py
oarepo_global_search/i18n/webpack.py
oarepo_global_search/i18n/semantic-ui/translations/oarepo_global_search/i18next.js
oarepo_global_search/i18n/semantic-ui/translations/oarepo_global_search/messages/index.js
oarepo_global_search/i18n/semantic-ui/translations/oarepo_global_search/messages/cs/LC_MESSAGES/translations.json
oarepo_global_search/i18n/semantic-ui/translations/oarepo_global_search/messages/en/LC_MESSAGES/translations.json
oarepo_global_search/i18n/translations/messages.pot
oarepo_global_search/i18n/translations/cs/LC_MESSAGES/messages.po
oarepo_global_search/i18n/translations/en/LC_MESSAGES/messages.po
oarepo_global_search/resources/__init__.py
oarepo_global_search/resources/records/__init__.py
oarepo_global_search/resources/records/config.py
oarepo_global_search/resources/records/resource.py
oarepo_global_search/resources/records/response.py
oarepo_global_search/services/__init__.py
oarepo_global_search/services/records/__init__.py
oarepo_global_search/services/records/api.py
oarepo_global_search/services/records/config.py
oarepo_global_search/services/records/exceptions.py
oarepo_global_search/services/records/params.py
oarepo_global_search/services/records/permissions.py
oarepo_global_search/services/records/results.py
oarepo_global_search/services/records/search.py
oarepo_global_search/services/records/service.py
oarepo_global_search/ui/__init__.py
oarepo_global_search/ui/config.py
oarepo_global_search/ui/views.py
oarepo_global_search/ui/oarepo_global_search/__init__.py
oarepo_global_search/ui/oarepo_global_search/webpack.py
oarepo_global_search/ui/oarepo_global_search/semantic-ui/js/oarepo_global_search/search/index.js
oarepo_global_search/ui/templates/semantic-ui/global_search/NoModels.jinja
oarepo_global_search-1.0.45.dist-info/METADATA
oarepo_global_search-1.0.45.dist-info/WHEEL
oarepo_global_search-1.0.45.dist-info/entry_points.txt
oarepo_global_search-1.0.45.dist-info/top_level.txt
oarepo_global_search-1.0.45.dist-info/RECORD
