Metadata-Version: 2.4
Name: oarepo-global-search
Version: 1.0.45
Summary: "A model builder plugin for global search"
Home-page: https://github.com/oarepo/oarepo-global-search
Author: Alzbeta Pokorna
Author-email: Alzbeta.Pokorna@cesnet.cz
License: MIT
Keywords: invenio relations model builder
Platform: any
Classifier: Development Status :: 3 - Alpha
Requires-Python: >=3.10
Requires-Dist: oarepo-ui
Provides-Extra: tests
Requires-Dist: pytest; extra == "tests"
Requires-Dist: black; extra == "tests"
Requires-Dist: autoflake; extra == "tests"
Requires-Dist: isort; extra == "tests"
Requires-Dist: pytest-oarepo; extra == "tests"
